{
  "columns": [
    {
      "span": 4,
      "memberGroups": {
        "Owner": {
          "members": {
            "owner": {},
            "description": {}
          }
        }
      }
    },
    {
      "span": 4,
      "memberGroups": {
        "Phone": {
          "members": {
            "phoneNumber": {}
          }
        }
      }
    },
    {
      "span": 4,
      "memberGroups": {
        "Status": {
          "members": {
            "legal": {},
            "status": {},
            "type": {},
            "reference": {}
          }
        }
      }
    },
    {
      "span": 0,
      "collections": {}
    }
  ],
  "actions": {
    "lock": {},
    "unlock": {}
  }
}