{
  "columns": [
    {
      "span": 4,
      "memberGroups": {
        "General": {
          "members": {
            "reference": {},
            "name": {},
            "bankAccount": {
              "actions": {
                "changeBankAccount": {}
              }
            },
            "sepaMandateIdentifier": {},
            "sequenceType" : {},
            "scheme": {
              "actions": {
                "change": {}
              }
            }
          }
        },
        "Parties": {
          "members": {
            "primaryParty": {},
            "secondaryParty": {}
          }
        },
        "Application Level": {
          "members": {
            "applicationTenancy": {
              "hidden": {"where": "ALL_TABLES"},
              "disabled": {}
            }
          }
        }
      }
    },
    {
      "span": 3,
      "memberGroups": {
        "Dates": {
          "members": {
            "startDate": {},
            "endDate": {
              "actions": {
                "changeDates": {}
              }
            },
            "signatureDate": {
              "actions": {
                "changeSignatureDate": {}
              }
            },
            "terminationDate": {},
            "current": {}
          }
        },
        "Related": {
          "members": {
            "next": {},
            "previous": {
              "actions": {
                "changePrevious": {}
              }
            }
          }
        }
      }
    },
    {
      "span": 0,
      "memberGroups": {}
    },
    {
      "span": 5,
      "collections": {
        "roles": {
          "actions": {
            "createInitialRole": {}
          }
        }
      }
    }
  ],
  "actions": {
  }
}